pyvlbi/__init__.py
pyvlbi/ant.so
pyvlbi/conv.so
pyvlbi/gravdelay.py
pyvlbi/orb.so
pyvlbi/plot.so
pyvlbi/sat.so
pyvlbi/set.so
pyvlbi/vlbi.so
pyvlbi/vpipe.so
pyvlbi/ant/ALMA.ant
pyvlbi/ant/APEX.ant
pyvlbi/ant/CARMA.ant
pyvlbi/ant/CBS.ant
pyvlbi/ant/CSO.ant
pyvlbi/ant/EB.ant
pyvlbi/ant/FAST.ant
pyvlbi/ant/GBT.ant
pyvlbi/ant/GLT.ant
pyvlbi/ant/JCMT.ant
pyvlbi/ant/KM40.ant
pyvlbi/ant/KP12.ant
pyvlbi/ant/LMT.ant
pyvlbi/ant/MY50.ant
pyvlbi/ant/NOEMA.ant
pyvlbi/ant/PK.ant
pyvlbi/ant/PV30.ant
pyvlbi/ant/RKZ.ant
pyvlbi/ant/SMA.ant
pyvlbi/ant/SMT.ant
pyvlbi/ant/SPT.ant
pyvlbi/ant/SR.ant
pyvlbi/ant/TM65.ant
pyvlbi/ant/UR26.ant
pyvlbi/ant/VLBA_BR.ant
pyvlbi/ant/VLBA_FD.ant
pyvlbi/ant/VLBA_HN.ant
pyvlbi/ant/VLBA_KP.ant
pyvlbi/ant/VLBA_LA.ant
pyvlbi/ant/VLBA_MK.ant
pyvlbi/ant/VLBA_NL.ant
pyvlbi/ant/VLBA_OV.ant
pyvlbi/ant/VLBA_PT.ant
pyvlbi/ant/VLBA_SC.ant
pyvlbi/models/2k_earth_daymap.jpg
pyvlbi/models/2k_moon.jpg
pyvlbi/models/8k_earth_daymap.jpg
pyvlbi/models/8k_moon.jpg
pyvlbi/models/ulysses.obj
pyvlbi/sat/Capella1.sat
pyvlbi/sat/Capella2.sat
pyvlbi/sat/Capella3.sat
pyvlbi/sat/Capella4.sat
pyvlbi/sat/INTEGRAL.sat
pyvlbi/sat/INTEGRAL_TLE.dat
pyvlbi/sat/LOVEX.sat
pyvlbi/sat/MMT.sat
pyvlbi/sat/Queqiao3.sat
pyvlbi/sat/RadioAstro_TLE.dat
pyvlbi/sat/RadioAstron.sat
pyvlbi/sat/THEZA.sat
pyvlbi/sat/de440s.bsp
pyvlbi-0.1.dist-info/METADATA
pyvlbi-0.1.dist-info/WHEEL
pyvlbi-0.1.dist-info/top_level.txt
pyvlbi-0.1.dist-info/RECORD
